<?xml version="1.0" encoding="UTF-8"?>
<java version="1.6.0_22" class="java.beans.XMLDecoder">
 <object class="net.sourceforge.ondex.ovtk2.ui.popup.custom.CustomPopupItemBean">
  <void property="code">
   <string>function main() {
	var i = getPickedConcepts().iterator()
	while(i.hasNext()) {
		doLayout(i.next())
	}
}

function doLayout(concept) {
	var a = getAssociatedConceptIDs(concept, true)
	layoutNeighbours(concept.getId(), a)
}

main()</string>
  </void>
  <void property="libraries">
   <string>toolbox.js</string>
  </void>
  <void property="name">
   <string>layout Neighbours</string>
  </void>
 </object>
</java>
